{"_type":"export","__export_format":4,"__export_date":"2022-02-09T01:01:58.530Z","__export_source":"insomnia.desktop.app:v2021.7.2","resources":[{"_id":"req_005d0919ad1b4009a49e48a7f96b4260","parentId":"fld_7e79cddb90a74a1d9f55861299cc6c77","modified":1644363786196,"created":1644359068690,"url":"{{ _.base_url }}delivery","name":"Create delivery","description":"","method":"POST","body":{"mimeType":"application/json","text":"{\n\t\"item_name\": \"pizza\"\n}"},"parameters":[],"headers":[{"name":"Content-Type","value":"application/json","id":"pair_966809e4a906464ba5a30e6d9ca549e8"}],"authentication":{"type":"bearer","token":"{{ _.token_client }}"},"metaSortKey":-1644359068690,"isPrivate":false,"settingStoreCookies":true,"settingSendCookies":true,"settingDisableRenderRequestBody":false,"settingEncodeUrl":true,"settingRebuildPath":true,"settingFollowRedirects":"global","_type":"request"},{"_id":"fld_7e79cddb90a74a1d9f55861299cc6c77","parentId":"wrk_aed507f38b5f43a1bd9705e86b499453","modified":1644359055035,"created":1644359055035,"name":"Delivery","description":"","environment":{},"environmentPropertyOrder":null,"metaSortKey":-1644359055035,"_type":"request_group"},{"_id":"wrk_aed507f38b5f43a1bd9705e86b499453","parentId":null,"modified":1644273360432,"created":1644273360432,"name":"Delivery-API","description":"","scope":"collection","_type":"workspace"},{"_id":"req_f7f94e59b6f84e56a3cf22bb90404cb8","parentId":"fld_7e79cddb90a74a1d9f55861299cc6c77","modified":1644367495292,"created":1644361728533,"url":"{{ _.base_url }}delivery/available","name":"Find all Available","description":"","method":"GET","body":{},"parameters":[],"headers":[],"authentication":{"type":"bearer","token":"{{ _.token_deliveryman }}","disabled":false},"metaSortKey":-1644316257419,"isPrivate":false,"settingStoreCookies":true,"settingSendCookies":true,"settingDisableRenderRequestBody":false,"settingEncodeUrl":true,"settingRebuildPath":true,"settingFollowRedirects":"global","_type":"request"},{"_id":"req_c717484a0e61485fb772fac306485db3","parentId":"fld_7e79cddb90a74a1d9f55861299cc6c77","modified":1644367580299,"created":1644363578518,"url":"{{ _.base_url }}delivery/update-deliveryman/{% response 'body', 'req_f7f94e59b6f84e56a3cf22bb90404cb8', 'b64::JC5bMF0uaWQ=::46b', 'always', 60 %}","name":"Update deliveryman","description":"","method":"PUT","body":{},"parameters":[],"headers":[],"authentication":{"type":"bearer","token":"{{ _.token_deliveryman }}","disabled":false},"metaSortKey":-1644294851783.5,"isPrivate":false,"settingStoreCookies":true,"settingSendCookies":true,"settingDisableRenderRequestBody":false,"settingEncodeUrl":true,"settingRebuildPath":true,"settingFollowRedirects":"global","_type":"request"},{"_id":"req_fcca1cf3ceb145089623f60cbe2f3b41","parentId":"fld_7e79cddb90a74a1d9f55861299cc6c77","modified":1644368495047,"created":1644367462483,"url":"{{ _.base_url }}delivery/update-end-date/fc11fc46-228f-4a76-b301-f1ac3bc559e7","name":"Update end date","description":"","method":"PUT","body":{},"parameters":[],"headers":[],"authentication":{"type":"bearer","token":"{{ _.token_deliveryman }}","disabled":false},"metaSortKey":-1644284148990.75,"isPrivate":false,"settingStoreCookies":true,"settingSendCookies":true,"settingDisableRenderRequestBody":false,"settingEncodeUrl":true,"settingRebuildPath":true,"settingFollowRedirects":"global","_type":"request"},{"_id":"req_c6a17d5c1021474d9f7f4f925ff73296","parentId":"fld_9ccd4cd018f64620a2cd518b5bb4cb11","modified":1644366109732,"created":1644364750844,"url":"{{ _.base_url }}client/deliveries","name":"Find all delivery for client","description":"","method":"GET","body":{},"parameters":[],"headers":[],"authentication":{"type":"bearer","token":"{{ _.token_client }}"},"metaSortKey":-1644273446198,"isPrivate":false,"settingStoreCookies":true,"settingSendCookies":true,"settingDisableRenderRequestBody":false,"settingEncodeUrl":true,"settingRebuildPath":true,"settingFollowRedirects":"global","_type":"request"},{"_id":"fld_9ccd4cd018f64620a2cd518b5bb4cb11","parentId":"wrk_aed507f38b5f43a1bd9705e86b499453","modified":1644273424180,"created":1644273424180,"name":"Client","description":"","environment":{},"environmentPropertyOrder":null,"metaSortKey":-1644273424180,"_type":"request_group"},{"_id":"req_8fb0caad973f457da52a835f42e8737d","parentId":"fld_9ccd4cd018f64620a2cd518b5bb4cb11","modified":1644365653755,"created":1644273446148,"url":"{{ _.base_url }}client","name":"Create client","description":"","method":"POST","body":{"mimeType":"application/json","text":"{\n\t\"username\": \"client@email.com\",\n\t\"password\": \"test123\"\n}"},"parameters":[],"headers":[{"name":"Content-Type","value":"application/json","id":"pair_0c049e9dd5504174970e58ea3c329a69"}],"authentication":{},"metaSortKey":-1644273446148,"isPrivate":false,"settingStoreCookies":true,"settingSendCookies":true,"settingDisableRenderRequestBody":false,"settingEncodeUrl":true,"settingRebuildPath":true,"settingFollowRedirects":"global","_type":"request"},{"_id":"req_be759924e65846f4910abb06e96a93ed","parentId":"fld_9ccd4cd018f64620a2cd518b5bb4cb11","modified":1644362296970,"created":1644275890950,"url":"{{ _.base_url }}client/authenticate","name":"Authenticate","description":"","method":"POST","body":{"mimeType":"application/json","text":"{\n\t\"username\": \"client@email.com\",\n\t\"password\": \"test123\"\n}"},"parameters":[],"headers":[{"name":"Content-Type","value":"application/json","id":"pair_0c049e9dd5504174970e58ea3c329a69"}],"authentication":{},"metaSortKey":-1643920580193.5,"isPrivate":false,"settingStoreCookies":true,"settingSendCookies":true,"settingDisableRenderRequestBody":false,"settingEncodeUrl":true,"settingRebuildPath":true,"settingFollowRedirects":"global","_type":"request"},{"_id":"req_eb28bd961da64c2a84272cc5dcaa2c3a","parentId":"fld_af7daafa198846819870286f3ceaffc7","modified":1644367027855,"created":1644366102424,"url":"{{ _.base_url }}deliveryman/deliveries","name":"Find all delivery for deliveryman","description":"","method":"GET","body":{},"parameters":[],"headers":[],"authentication":{"type":"bearer","token":"{{ _.token_deliveryman }}","disabled":false},"metaSortKey":-1644097013220.75,"isPrivate":false,"settingStoreCookies":true,"settingSendCookies":true,"settingDisableRenderRequestBody":false,"settingEncodeUrl":true,"settingRebuildPath":true,"settingFollowRedirects":"global","_type":"request"},{"_id":"fld_af7daafa198846819870286f3ceaffc7","parentId":"wrk_aed507f38b5f43a1bd9705e86b499453","modified":1644277710402,"created":1644277710402,"name":"Deliveryman","description":"","environment":{},"environmentPropertyOrder":null,"metaSortKey":-1643747516467,"_type":"request_group"},{"_id":"req_ae79bba207dd46218f8fa85c82d8ac2a","parentId":"fld_af7daafa198846819870286f3ceaffc7","modified":1644365643673,"created":1644277710437,"url":"{{ _.base_url }}deliveryman","name":"Create deliveryman","description":"","method":"POST","body":{"mimeType":"application/json","text":"{\n\t\"username\": \"delyveryman@email.com\",\n\t\"password\": \"test123\"\n}"},"parameters":[],"headers":[{"name":"Content-Type","value":"application/json","id":"pair_0c049e9dd5504174970e58ea3c329a69"}],"authentication":{},"metaSortKey":-1644097013170.75,"isPrivate":false,"settingStoreCookies":true,"settingSendCookies":true,"settingDisableRenderRequestBody":false,"settingEncodeUrl":true,"settingRebuildPath":true,"settingFollowRedirects":"global","_type":"request"},{"_id":"req_a8d4ade10632472d85842d7a9af88206","parentId":"fld_af7daafa198846819870286f3ceaffc7","modified":1644362313931,"created":1644277710432,"url":"{{ _.base_url }}deliveryman/authenticate","name":"Authenticate","description":"","method":"POST","body":{"mimeType":"application/json","text":"{\n\t\"username\": \"client@email.com\",\n\t\"password\": \"test123\"\n}"},"parameters":[],"headers":[{"name":"Content-Type","value":"application/json","id":"pair_0c049e9dd5504174970e58ea3c329a69"}],"authentication":{},"metaSortKey":-1643920580193.5,"isPrivate":false,"settingStoreCookies":true,"settingSendCookies":true,"settingDisableRenderRequestBody":false,"settingEncodeUrl":true,"settingRebuildPath":true,"settingFollowRedirects":"global","_type":"request"},{"_id":"env_39a3b8b078b80d6def596a4ef0c9a920d550bd65","parentId":"wrk_aed507f38b5f43a1bd9705e86b499453","modified":1644362176063,"created":1644273360437,"name":"Base Environment","data":{"base_url":"http://localhost:3000/","token_deliveryman":"{% response 'body', 'req_a8d4ade10632472d85842d7a9af88206', 'b64::JC50b2tlbg==::46b', 'always', 60 %}","token_client":"{% response 'body', 'req_be759924e65846f4910abb06e96a93ed', 'b64::JC50b2tlbg==::46b', 'always', 60 %}"},"dataPropertyOrder":{"&":["base_url","token_deliveryman","token_client"]},"color":null,"isPrivate":false,"metaSortKey":1644273360437,"_type":"environment"},{"_id":"jar_39a3b8b078b80d6def596a4ef0c9a920d550bd65","parentId":"wrk_aed507f38b5f43a1bd9705e86b499453","modified":1644273360439,"created":1644273360439,"name":"Default Jar","cookies":[],"_type":"cookie_jar"},{"_id":"spc_dfa2f394c62d4fbcac23a4e4cf6b03bd","parentId":"wrk_aed507f38b5f43a1bd9705e86b499453","modified":1644273360433,"created":1644273360433,"fileName":"Delivery-API","contents":"","contentType":"yaml","_type":"api_spec"}]}